{
  "timestamp": "2025-09-04T22:40:33.335Z",
  "checkCount": 15,
  "results": {
    "development": {
      "branch": "development",
      "timestamp": 1757025633336,
      "status": "HEALTHY",
      "logs": [
        {
          "type": "ERROR",
          "timestamp": 1757025635215,
          "content": "Failed to get logs: Command failed: railway logs --service development -n 200\nerror: unexpected argument '-n' found\n\n  tip: to pass '-n' as a value, use '-- -n'\n\nUsage: railway.exe logs [OPTIONS] [DEPLOYMENT_ID]\n\nFor more information, try '--help'.\n\n"
        },
        {
          "type": "GIT_COMMITS",
          "timestamp": 1757025635316,
          "content": "7bd65ca fix: ensure Phase 4 widgets are included in dashboard\n323ec1b fix: ensure Phase 4 widgets are included in dashboard\nf108839 fix: ensure Phase 4 widgets are included in dashboard\neea6b5c fix: ensure Phase 4 widgets are included in dashboard\n256a97b fix: ensure Phase 4 widgets are included in dashboard\n"
        }
      ],
      "errors": [],
      "build": null,
      "deployment": "SUCCESS",
      "health": {
        "healthy": true,
        "statusCode": 200,
        "responseTime": 231,
        "hasPhase4": false
      }
    },
    "test": {
      "branch": "test",
      "timestamp": 1757025635547,
      "status": "HEALTHY",
      "logs": [
        {
          "type": "ERROR",
          "timestamp": 1757025636065,
          "content": "Failed to get logs: Command failed: railway logs --service test -n 200\nerror: unexpected argument '-n' found\n\n  tip: to pass '-n' as a value, use '-- -n'\n\nUsage: railway.exe logs [OPTIONS] [DEPLOYMENT_ID]\n\nFor more information, try '--help'.\n\n"
        },
        {
          "type": "GIT_COMMITS",
          "timestamp": 1757025636110,
          "content": "8093604 Merge branch 'development' into test\n7bd65ca fix: ensure Phase 4 widgets are included in dashboard\n49351a2 Merge branch 'development' into test\n323ec1b fix: ensure Phase 4 widgets are included in dashboard\n07814f7 Merge branch 'development' into test\n"
        }
      ],
      "errors": [],
      "build": null,
      "deployment": "SUCCESS",
      "health": {
        "healthy": true,
        "statusCode": 200,
        "responseTime": 93,
        "hasPhase4": false
      }
    },
    "production": {
      "branch": "production",
      "timestamp": 1757025636204,
      "status": "HEALTHY",
      "logs": [
        {
          "type": "ERROR",
          "timestamp": 1757025636576,
          "content": "Failed to get logs: Command failed: railway logs --service production -n 200\nerror: unexpected argument '-n' found\n\n  tip: to pass '-n' as a value, use '-- -n'\n\nUsage: railway.exe logs [OPTIONS] [DEPLOYMENT_ID]\n\nFor more information, try '--help'.\n\n"
        },
        {
          "type": "GIT_COMMITS",
          "timestamp": 1757025636618,
          "content": "7eaca0e Merge branch 'development' into production\n7bd65ca fix: ensure Phase 4 widgets are included in dashboard\n22caac0 Merge branch 'development' into production\n323ec1b fix: ensure Phase 4 widgets are included in dashboard\n7f76259 Merge branch 'development' into production\n"
        }
      ],
      "errors": [],
      "build": null,
      "deployment": "SUCCESS",
      "health": {
        "healthy": true,
        "statusCode": 200,
        "responseTime": 146,
        "hasPhase4": false
      }
    }
  },
  "summary": {
    "healthy": 3,
    "building": 0,
    "failed": 0,
    "unknown": 0
  }
}