{
  "timestamp": "2025-09-04T23:37:38.600Z",
  "checkCount": 6,
  "results": {
    "development": {
      "branch": "development",
      "timestamp": 1757029058600,
      "status": "HEALTHY",
      "logs": [
        {
          "type": "ERROR",
          "timestamp": 1757029058881,
          "content": "Failed to get logs: Command failed: railway logs --service development --deployment\nNo linked project found. Run railway link to connect to a project\n"
        },
        {
          "type": "GIT_COMMITS",
          "timestamp": 1757029058924,
          "content": "e4813c3 fix: ensure Phase 4 widgets are included in dashboard\naeda0dc fix: ensure Phase 4 widgets are included in dashboard\nf2fc011 fix: ensure Phase 4 widgets are included in dashboard\n844fd66 fix: ensure Phase 4 widgets are included in dashboard\n8575b14 fix: ensure Phase 4 widgets are included in dashboard\n"
        }
      ],
      "errors": [],
      "build": null,
      "deployment": "SUCCESS",
      "health": {
        "healthy": true,
        "statusCode": 200,
        "responseTime": 217,
        "hasPhase4": false
      }
    },
    "test": {
      "branch": "test",
      "timestamp": 1757029059141,
      "status": "HEALTHY",
      "logs": [
        {
          "type": "ERROR",
          "timestamp": 1757029059641,
          "content": "Failed to get logs: Command failed: railway logs --service test --deployment\nNo linked project found. Run railway link to connect to a project\n"
        },
        {
          "type": "GIT_COMMITS",
          "timestamp": 1757029059685,
          "content": "da6c599 Merge branch 'development' into test\ne4813c3 fix: ensure Phase 4 widgets are included in dashboard\n06487b8 Merge branch 'development' into test\naeda0dc fix: ensure Phase 4 widgets are included in dashboard\n98d308f Merge branch 'development' into test\n"
        }
      ],
      "errors": [],
      "build": null,
      "deployment": "SUCCESS",
      "health": {
        "healthy": true,
        "statusCode": 200,
        "responseTime": 79,
        "hasPhase4": false
      }
    },
    "production": {
      "branch": "production",
      "timestamp": 1757029059764,
      "status": "HEALTHY",
      "logs": [
        {
          "type": "ERROR",
          "timestamp": 1757029060105,
          "content": "Failed to get logs: Command failed: railway logs --service production --deployment\nNo linked project found. Run railway link to connect to a project\n"
        },
        {
          "type": "GIT_COMMITS",
          "timestamp": 1757029060145,
          "content": "4856818 Merge branch 'development' into production\ne4813c3 fix: ensure Phase 4 widgets are included in dashboard\nfff7c6a Merge branch 'development' into production\naeda0dc fix: ensure Phase 4 widgets are included in dashboard\n8f37bba Merge branch 'development' into production\n"
        }
      ],
      "errors": [],
      "build": null,
      "deployment": "SUCCESS",
      "health": {
        "healthy": true,
        "statusCode": 200,
        "responseTime": 132,
        "hasPhase4": false
      }
    }
  },
  "summary": {
    "healthy": 3,
    "building": 0,
    "failed": 0,
    "unknown": 0
  }
}